autotreemodel/__init__.py
autotreemodel/auto_build_tree_model.py
autotreemodel/autotreemodel.py
autotreemodel/bayes_opt_tuner.py
autotreemodel/cli.py
autotreemodel/feature_selection_2_treemodel.py
autotreemodel/logger_utils.py
autotreemodel/plot_metrics.py
autotreemodel/utils.py
autotreemodel-0.1.6.dist-info/AUTHORS.rst
autotreemodel-0.1.6.dist-info/LICENSE
autotreemodel-0.1.6.dist-info/METADATA
autotreemodel-0.1.6.dist-info/WHEEL
autotreemodel-0.1.6.dist-info/entry_points.txt
autotreemodel-0.1.6.dist-info/top_level.txt
autotreemodel-0.1.6.dist-info/RECORD
