Metadata-Version: 2.1
Name: autotreemodel
Version: 0.1.6
Summary: auto build a tree model
Home-page: https://github.com/ZhengRyan/autotreemodel
Author: RyanZheng
Author-email: zhengruiping000@163.com
License: MIT license
Keywords: autotreemodel
Platform: UNKNOWN
Classifier: Development Status :: 2 - Pre-Alpha
Classifier: Intended Audience :: Developers
Classifier: License :: OSI Approved :: MIT License
Classifier: Natural Language :: English
Classifier: Programming Language :: Python :: 3
Classifier: Programming Language :: Python :: 3.6
Classifier: Programming Language :: Python :: 3.7
Classifier: Programming Language :: Python :: 3.8
Requires-Python: >=3.6
Requires-Dist: bayesian-optimization (==1.1.0)
Requires-Dist: joblib (>=0.12)
Requires-Dist: lightgbm (==3.2.1)
Requires-Dist: pandas
Requires-Dist: shap (==0.36.0)
Requires-Dist: xgboost (==1.2.0)
Requires-Dist: scikit-learn (==0.21)
Requires-Dist: matplotlib (==3.1.2)
